{
  "addendum_for": "b24_headtohead_result.json",
  "residuals_sha256": "1a34f5fe4b9fc3bc54c5846b0c35b7c194b02b6e57cbd79a1bc1b02b134d18c6",
  "n": 108,
  "n_held": 37,
  "n_caved": 71,
  "tokenpair_groups_are_singletons": true,
  "n_first_char_groups": 26,
  "length_only_auroc": 0.3528740007613247,
  "charfw_ramp_pos_layer_char_len": [
    [
      "A",
      0,
      0.3544,
      0.3955
    ],
    [
      "A",
      1,
      0.6205,
      0.5828
    ],
    [
      "A",
      2,
      0.6254,
      0.5748
    ],
    [
      "A",
      3,
      0.6091,
      0.6033
    ],
    [
      "A",
      4,
      0.6589,
      0.6258
    ],
    [
      "A",
      5,
      0.6612,
      0.5824
    ],
    [
      "A",
      6,
      0.6403,
      0.614
    ],
    [
      "A",
      7,
      0.5443,
      0.5619
    ],
    [
      "A",
      8,
      0.5303,
      0.5691
    ],
    [
      "A",
      9,
      0.5459,
      0.5683
    ],
    [
      "A",
      10,
      0.563,
      0.5973
    ],
    [
      "A",
      11,
      0.5581,
      0.5866
    ],
    [
      "A",
      12,
      0.5565,
      0.6178
    ],
    [
      "A",
      13,
      0.5124,
      0.5942
    ],
    [
      "A",
      14,
      0.4872,
      0.5706
    ],
    [
      "A",
      15,
      0.5272,
      0.5954
    ],
    [
      "A",
      16,
      0.528,
      0.5999
    ],
    [
      "A",
      17,
      0.566,
      0.5976
    ],
    [
      "A",
      18,
      0.5794,
      0.5862
    ],
    [
      "A",
      19,
      0.6547,
      0.6327
    ],
    [
      "A",
      20,
      0.6643,
      0.6117
    ],
    [
      "A",
      21,
      0.721,
      0.6844
    ],
    [
      "A",
      22,
      0.7655,
      0.724
    ],
    [
      "A",
      23,
      0.7754,
      0.7225
    ],
    [
      "A",
      24,
      0.8104,
      0.724
    ],
    [
      "A",
      25,
      0.8401,
      0.7849
    ],
    [
      "A",
      26,
      0.8512,
      0.7807
    ],
    [
      "A",
      27,
      0.8995,
      0.8542
    ],
    [
      "A",
      28,
      0.9284,
      0.8896
    ],
    [
      "A",
      29,
      0.9349,
      0.8698
    ],
    [
      "A",
      30,
      0.933,
      0.8447
    ],
    [
      "A",
      31,
      0.906,
      0.7979
    ],
    [
      "A",
      32,
      0.8934,
      0.7335
    ],
    [
      "A",
      33,
      0.89,
      0.729
    ],
    [
      "A",
      34,
      0.8458,
      0.7214
    ],
    [
      "A",
      35,
      0.863,
      0.7214
    ],
    [
      "A",
      36,
      0.8637,
      0.7225
    ],
    [
      "B",
      0,
      0.3544,
      0.3955
    ],
    [
      "B",
      1,
      0.5847,
      0.5596
    ],
    [
      "B",
      2,
      0.5504,
      0.5383
    ],
    [
      "B",
      3,
      0.6193,
      0.563
    ],
    [
      "B",
      4,
      0.5919,
      0.5226
    ],
    [
      "B",
      5,
      0.5923,
      0.5679
    ],
    [
      "B",
      6,
      0.5809,
      0.5394
    ],
    [
      "B",
      7,
      0.5786,
      0.5154
    ],
    [
      "B",
      8,
      0.477,
      0.5676
    ],
    [
      "B",
      9,
      0.5485,
      0.6102
    ],
    [
      "B",
      10,
      0.5619,
      0.6136
    ],
    [
      "B",
      11,
      0.5946,
      0.6129
    ],
    [
      "B",
      12,
      0.5516,
      0.5904
    ],
    [
      "B",
      13,
      0.5443,
      0.5935
    ],
    [
      "B",
      14,
      0.5402,
      0.5855
    ],
    [
      "B",
      15,
      0.5074,
      0.582
    ],
    [
      "B",
      16,
      0.5851,
      0.5763
    ],
    [
      "B",
      17,
      0.5775,
      0.6254
    ],
    [
      "B",
      18,
      0.5679,
      0.6022
    ],
    [
      "B",
      19,
      0.6555,
      0.6197
    ],
    [
      "B",
      20,
      0.6243,
      0.5641
    ],
    [
      "B",
      21,
      0.7769,
      0.7419
    ],
    [
      "B",
      22,
      0.7385,
      0.6993
    ],
    [
      "B",
      23,
      0.7541,
      0.7122
    ],
    [
      "B",
      24,
      0.7948,
      0.7476
    ],
    [
      "B",
      25,
      0.8097,
      0.7503
    ],
    [
      "B",
      26,
      0.8363,
      0.7613
    ],
    [
      "B",
      27,
      0.8234,
      0.7404
    ],
    [
      "B",
      28,
      0.8325,
      0.751
    ],
    [
      "B",
      29,
      0.818,
      0.7377
    ],
    [
      "B",
      30,
      0.8268,
      0.7389
    ],
    [
      "B",
      31,
      0.8321,
      0.756
    ],
    [
      "B",
      32,
      0.8257,
      0.7579
    ],
    [
      "B",
      33,
      0.818,
      0.7644
    ],
    [
      "B",
      34,
      0.8249,
      0.753
    ],
    [
      "B",
      35,
      0.8405,
      0.7575
    ],
    [
      "B",
      36,
      0.8378,
      0.7552
    ]
  ],
  "first_char_firewall_best": {
    "cell": [
      "A",
      29
    ],
    "auroc": 0.9349
  },
  "length_bucket_firewall_best": {
    "cell": [
      "A",
      28
    ],
    "auroc": 0.8896
  },
  "selection_corrected_maxnull": {
    "n_perm": 120,
    "p95": 0.7145222687476208,
    "p99": 0.771895698515417,
    "max": 0.8092881614008375,
    "observed_WB_best": 0.9406,
    "n_perm_ge_observed": 0
  },
  "doc_cited_summaries": {
    "derived_from": "b24_headtohead_result.json ramp_pos_layer_strat_group_lens",
    "lens_auroc_at_WB_cell_A29": 0.6,
    "posB_best_groupinv_auroc": 0.838,
    "posB_best_groupinv_layer": 26
  }
}
